sales_pred_filiankova/__init__.py
sales_pred_filiankova/version.py
sales_pred_filiankova/analysis/__init__.py
sales_pred_filiankova/analysis/error_analysis.py
sales_pred_filiankova/analysis/shap_explainer.py
sales_pred_filiankova/data/DQC.py
sales_pred_filiankova/data/ETL.py
sales_pred_filiankova/data/__init__.py
sales_pred_filiankova/features/__init__.py
sales_pred_filiankova/features/feature_engineering.py
sales_pred_filiankova/features/feature_extractor.py
sales_pred_filiankova/features/preprocessing.py
sales_pred_filiankova/features/validation_schema.py
sales_pred_filiankova/models/__init__.py
sales_pred_filiankova/models/feature_selection.py
sales_pred_filiankova/models/submission.py
sales_pred_filiankova/models/train_model.py
sales_pred_filiankova/models/tuning.py
sales_pred_filiankova-1.3.9.dist-info/LICENSE
sales_pred_filiankova-1.3.9.dist-info/METADATA
sales_pred_filiankova-1.3.9.dist-info/WHEEL
sales_pred_filiankova-1.3.9.dist-info/top_level.txt
sales_pred_filiankova-1.3.9.dist-info/RECORD
