Metadata-Version: 2.1
Name: sales-pred-filiankova
Version: 1.3.9
Summary: test package upload
Author-email: Maryia Filiankova <maryia.filenkova@gmail.com>
License: MIT License
Classifier: License :: OSI Approved :: MIT License
Classifier: Programming Language :: Python
Classifier: Programming Language :: Python :: 3
Requires-Python: >=3.7
License-File: LICENSE
Requires-Dist: pandas
Requires-Dist: numpy
Requires-Dist: shap
Requires-Dist: xgboost
Requires-Dist: scikit-learn
Requires-Dist: hyperopt
Requires-Dist: matplotlib
Requires-Dist: seaborn
Requires-Dist: boruta
Requires-Dist: category-encoders (>=2.6.0)
Requires-Dist: tqdm
Requires-Dist: ipython
